odoo10_addon_pos_product_template-10.0.2.1.1-py3.8-nspkg.pth
odoo/addons/pos_product_template/README.rst
odoo/addons/pos_product_template/__init__.py
odoo/addons/pos_product_template/__manifest__.py
odoo/addons/pos_product_template/demo/product_attribute_value.yml
odoo/addons/pos_product_template/demo/product_product.yml
odoo/addons/pos_product_template/demo/res_groups.yml
odoo/addons/pos_product_template/i18n/ca.po
odoo/addons/pos_product_template/i18n/es.po
odoo/addons/pos_product_template/i18n/fr.po
odoo/addons/pos_product_template/i18n/pos_product_template.pot
odoo/addons/pos_product_template/static/description/icon.png
odoo/addons/pos_product_template/static/src/css/ppt.css
odoo/addons/pos_product_template/static/src/img/screenshots/pos_product_template.png
odoo/addons/pos_product_template/static/src/js/ppt.js
odoo/addons/pos_product_template/static/src/xml/ppt.xml
odoo/addons/pos_product_template/view/view.xml
odoo10_addon_pos_product_template-10.0.2.1.1.dist-info/METADATA
odoo10_addon_pos_product_template-10.0.2.1.1.dist-info/WHEEL
odoo10_addon_pos_product_template-10.0.2.1.1.dist-info/namespace_packages.txt
odoo10_addon_pos_product_template-10.0.2.1.1.dist-info/top_level.txt
odoo10_addon_pos_product_template-10.0.2.1.1.dist-info/RECORD
